bach_generator/__init__.py
bach_generator/__main__.py
bach_generator/cli.py
bach_generator/py.typed
bach_generator/runner.py
bach_generator/gui/__init__.py
bach_generator/gui/args.py
bach_generator/gui/callbacks.py
bach_generator/gui/colour_cycle.py
bach_generator/gui/components.py
bach_generator/gui/config.py
bach_generator/gui/figure.py
bach_generator/gui/init.py
bach_generator/gui/media/icon.png
bach_generator/src/__init__.py
bach_generator/src/encoder.py
bach_generator/src/judge.py
bach_generator/src/manager.py
bach_generator/src/model.py
bach_generator/src/music_handler.py
bach_generator/src/output_handler.py
bach_generator-1.2.0.dist-info/LICENSE
bach_generator-1.2.0.dist-info/METADATA
bach_generator-1.2.0.dist-info/WHEEL
bach_generator-1.2.0.dist-info/top_level.txt
bach_generator-1.2.0.dist-info/RECORD
